setup.py
pydeploy/__init__.py
pydeploy/__version__.py
pydeploy/checkout_cache.py
pydeploy/command.py
pydeploy/environment.py
pydeploy/environment_utils.py
pydeploy/exceptions.py
pydeploy/installation_context.py
pydeploy/installer.py
pydeploy/os_api.py
pydeploy/python3_compat.py
pydeploy/remote.py
pydeploy/sources.py
pydeploy/virtualenv_api.py
pydeploy.egg-info/PKG-INFO
pydeploy.egg-info/SOURCES.txt
pydeploy.egg-info/dependency_links.txt
pydeploy.egg-info/entry_points.txt
pydeploy.egg-info/requires.txt
pydeploy.egg-info/top_level.txt
pydeploy/entry_points/__init__.py
pydeploy/entry_points/pydeploy.py
pydeploy/scm/__init__.py
pydeploy/scm/git.py